rstats/__init__.py
rstats/avg.py
rstats/bench.py
rstats/counter.py
rstats/format.py
rstats/prof.py
rstats/stats.py
rstats/time.py
rstats/types.py
rstats-0.6.0.dist-info/METADATA
rstats-0.6.0.dist-info/WHEEL
rstats-0.6.0.dist-info/RECORD
