Metadata-Version: 2.1
Name: rstats
Version: 0.6.0
Summary: Decorators for runtime statistics and benchmarking
Author: Emil Nikolov
Author-email: eenikolov@proton.me
Requires-Python: >=3.12,<4.0
Classifier: Programming Language :: Python :: 3
Classifier: Programming Language :: Python :: 3.12
Requires-Dist: humanize (>=4.8.0,<5.0.0)
Requires-Dist: pyyaml (>=6.0.1,<7.0.0)
Requires-Dist: rich (>=13.5.3,<14.0.0)
